aws_helper/__init__.py
aws_helper/helper.py
anjali_aws_helper-1.0.4.dist-info/LICENSE
anjali_aws_helper-1.0.4.dist-info/METADATA
anjali_aws_helper-1.0.4.dist-info/WHEEL
anjali_aws_helper-1.0.4.dist-info/top_level.txt
anjali_aws_helper-1.0.4.dist-info/RECORD
