Metadata-Version: 2.1
Name: anjali_aws_helper
Version: 1.0.4
License-File: LICENSE
Requires-Dist: boto3
